gaff/__init__.py
gaff-0.0.0a1.dist-info/METADATA
gaff-0.0.0a1.dist-info/WHEEL
gaff-0.0.0a1.dist-info/RECORD
